{
  "newDevices": [
    {
      "name": "Xreal One Pro",
      "manufacturer": "Xreal",
      "official_url": "https://us.shop.xreal.com/",
      "announced_date": "2024-12-04",
      "release_date": "2025-04-30",
      "price_usd": "599",
      "xr_category": "AR",
      "active_distribution": "Ja",
      "eol_status": "Aktiv oder ohne EOL-Angabe",
      "eol_date": "",
      "lifecycle_notes": "Flaggschiff-Display-Brille mit erster Flat-Prism-Optik (kein klassisches Birdbath), 57 Grad FOV; in China fuer 4.299 CNY (ca. 599 USD) gestartet.",
      "lifecycle_source": "https://eu.36kr.com/en/p/3394504308021635",
      "software": "Nebula OS",
      "compute_unit": "Tethered",
      "display_type": "Micro-OLED",
      "optics": "Flat-Prism (TIR)",
      "fov_horizontal_deg": "",
      "fov_vertical_deg": "",
      "fov_diagonal_deg": "57",
      "resolution_per_eye": "1920x1080",
      "refresh_hz": "120",
      "weight_g": "87",
      "tracking": "3DoF",
      "eye_tracking": "Nein",
      "hand_tracking": "Nein",
      "passthrough": "Nein (optische Durchsicht)",
      "chipset": "Xreal X1",
      "brightness_nits": "700",
      "connectivity": "USB-C DisplayPort",
      "audio": "Open-ear Stereo (Bose-Tuning)",
      "battery": "Via Host-Geraet",
      "ipd_mm": "Unklar",
      "prescription_support": "Ja (Einsaetze)",
      "camera": "Nein",
      "sources": ["https://eu.36kr.com/en/p/3394504308021635", "https://vr-compare.com/headset/xrealonepro", "https://www.tomshardware.com/peripherals/wearable-tech/xreal-one-pro-review"],
      "confidence": "high"
    },
    {
      "name": "X by Xreal a01",
      "manufacturer": "Xreal",
      "official_url": "https://tutorials.xreal.com/docs/glasses/xbxa01/",
      "announced_date": "2026-05-27",
      "release_date": "2026-05-27",
      "price_usd": "250",
      "xr_category": "AR",
      "active_distribution": "Ja",
      "eol_status": "Aktiv oder ohne EOL-Angabe",
      "eol_date": "",
      "lifecycle_notes": "Erstes Produkt der Budget-Submarke xbx, zunaechst nur China fuer 1.699 CNY (ca. 250 USD); US-Start im Juli 2026 fuer 299 USD.",
      "lifecycle_source": "https://www.gizmochina.com/2026/05/27/xreal-xbx-a01-ar-glasses-launched-specs-price/",
      "software": "Nebula OS",
      "compute_unit": "Tethered",
      "display_type": "Micro-OLED",
      "optics": "Birdbath",
      "fov_horizontal_deg": "",
      "fov_vertical_deg": "",
      "fov_diagonal_deg": "50",
      "resolution_per_eye": "1920x1080",
      "refresh_hz": "120",
      "weight_g": "62",
      "tracking": "3DoF",
      "eye_tracking": "Nein",
      "hand_tracking": "Nein",
      "passthrough": "Nein (optische Durchsicht)",
      "chipset": "Unklar",
      "brightness_nits": "1600",
      "connectivity": "USB-C DisplayPort",
      "audio": "Open-ear Stereo",
      "battery": "Via Host-Geraet",
      "ipd_mm": "Unklar",
      "prescription_support": "Unklar",
      "camera": "Nein",
      "sources": ["https://www.gizmochina.com/2026/05/27/xreal-xbx-a01-ar-glasses-launched-specs-price/", "https://www.auganix.org/ar-news-xreal-xbx-ar-glasses/", "https://finance.biggo.com/news/202605271221_XREAL_xbx_a01_AR_glasses_launch"],
      "confidence": "high"
    },
    {
      "name": "ARknovv A1",
      "manufacturer": "Gyges Labs",
      "official_url": "https://gygeslabs.com/",
      "announced_date": "2023-07-26",
      "release_date": "2023-09-26",
      "price_usd": "417",
      "xr_category": "AR",
      "active_distribution": "Unklar",
      "eol_status": "Aktiv oder ohne EOL-Angabe",
      "eol_date": "",
      "lifecycle_notes": "Birdbath-AR-Brille mit elektrochromen Glaesern und Aladdin OS; China-Start zu 2.988 CNY (ca. 417 USD), HUD-Version 3.988 CNY.",
      "lifecycle_source": "https://www.gizmochina.com/2023/07/26/arknovv-a1-ar-glass-wearable/",
      "software": "Aladdin OS",
      "compute_unit": "Tethered",
      "display_type": "Micro-OLED",
      "optics": "Birdbath",
      "fov_horizontal_deg": "",
      "fov_vertical_deg": "",
      "fov_diagonal_deg": "55",
      "resolution_per_eye": "1920x1080",
      "refresh_hz": "70",
      "weight_g": "68",
      "tracking": "3DoF",
      "eye_tracking": "Nein",
      "hand_tracking": "Nein",
      "passthrough": "Nein (optische Durchsicht)",
      "chipset": "Unklar",
      "brightness_nits": "Unklar",
      "connectivity": "USB-C, HDMI",
      "audio": "Open-ear Stereo",
      "battery": "Via Host-Geraet",
      "ipd_mm": "Unklar",
      "prescription_support": "Unklar",
      "camera": "Unklar",
      "sources": ["https://www.gizmochina.com/2023/07/26/arknovv-a1-ar-glass-wearable/", "https://www.ledinside.com/news/2023/7/2023_07_28_02"],
      "confidence": "medium"
    },
    {
      "name": "Leion Hey",
      "manufacturer": "LLVision",
      "official_url": "https://leion.glass/",
      "announced_date": "2023-04-26",
      "release_date": "2023-04-26",
      "price_usd": "620",
      "xr_category": "AR",
      "active_distribution": "Unklar",
      "eol_status": "Aktiv oder ohne EOL-Angabe",
      "eol_date": "",
      "lifecycle_notes": "AR-Uebersetzungsbrille der ersten Generation mit transparentem Wellenleiter; China-Aktionspreis 3.998 CNY (ca. 620 USD), ueber 30.000 Einheiten ausgeliefert.",
      "lifecycle_source": "https://www.abvr360.com/a/14550",
      "software": "Eigene Uebersetzungssoftware",
      "compute_unit": "Standalone",
      "display_type": "Micro-LED",
      "optics": "Waveguide",
      "fov_horizontal_deg": "",
      "fov_vertical_deg": "",
      "fov_diagonal_deg": "23",
      "resolution_per_eye": "Unklar",
      "refresh_hz": "Unklar",
      "weight_g": "79",
      "tracking": "None",
      "eye_tracking": "Nein",
      "hand_tracking": "Nein",
      "passthrough": "Nein (optische Durchsicht)",
      "chipset": "Qualcomm QCC4100",
      "brightness_nits": "1500",
      "connectivity": "Bluetooth, Wi-Fi",
      "audio": "Open-ear, Mikrofon-Array",
      "battery": "Integriert",
      "ipd_mm": "Unklar",
      "prescription_support": "Unklar",
      "camera": "Nein",
      "sources": ["https://www.abvr360.com/a/14550", "https://www.ledinside.cn/products/20230427-54941.html"],
      "confidence": "medium"
    },
    {
      "name": "Leion Hey2",
      "manufacturer": "LLVision",
      "official_url": "https://www.llvision.com/en/leion-pro.html",
      "announced_date": "2025-06-24",
      "release_date": "2025-06-24",
      "price_usd": "549",
      "xr_category": "AR",
      "active_distribution": "Ja",
      "eol_status": "Aktiv oder ohne EOL-Angabe",
      "eol_date": "",
      "lifecycle_notes": "AR-Uebersetzungsbrille mit gruenem Micro-LED-Wellenleiter und 100+ Sprachen; China 3.999 CNY, international 549 USD (Vorbestellung 499 USD).",
      "lifecycle_source": "https://finance.yahoo.com/news/llvision-launches-leion-hey2-ar-050500927.html",
      "software": "Eigene Uebersetzungssoftware",
      "compute_unit": "Standalone",
      "display_type": "Micro-LED",
      "optics": "Waveguide",
      "fov_horizontal_deg": "",
      "fov_vertical_deg": "",
      "fov_diagonal_deg": "25",
      "resolution_per_eye": "Unklar",
      "refresh_hz": "Unklar",
      "weight_g": "49",
      "tracking": "None",
      "eye_tracking": "Nein",
      "hand_tracking": "Nein",
      "passthrough": "Nein (optische Durchsicht, >90% Transparenz)",
      "chipset": "Xuanxuan 2800",
      "brightness_nits": "2500",
      "connectivity": "Bluetooth, Wi-Fi",
      "audio": "Vier-Mikrofon-Array (keine Lautsprecher)",
      "battery": "Integriert, 6-8h Uebersetzung (245 mAh)",
      "ipd_mm": "Unklar",
      "prescription_support": "Ja (Clip-on)",
      "camera": "Nein",
      "sources": ["https://finance.yahoo.com/news/llvision-launches-leion-hey2-ar-050500927.html", "https://www.52audio.com/archives/265991.html", "https://leion.glass/products/leion-hey-2-translation-ar-glasses"],
      "confidence": "high"
    },
    {
      "name": "Oppo Air Glass 2",
      "manufacturer": "Oppo",
      "official_url": "https://www.oppo.com/en/",
      "announced_date": "2022-12-14",
      "release_date": "2023",
      "price_usd": "Unklar",
      "xr_category": "AR",
      "active_distribution": "Nein",
      "eol_status": "EOL / Discontinued",
      "eol_date": "",
      "lifecycle_notes": "Leichte Monochrom-Wellenleiterbrille (SRG-Diffraktion) fuer Anrufe, Uebersetzung und Navigation; nur China, kein Preis offiziell genannt.",
      "lifecycle_source": "https://www.notebookcheck.net/OPPO-Air-Glass-2-debuts-as-a-new-light-and-accessibility-friendly-augmented-reality-product.674872.0.html",
      "software": "ColorOS / Air Glass",
      "compute_unit": "Smartphone",
      "display_type": "Micro LED",
      "optics": "Waveguide",
      "fov_horizontal_deg": "",
      "fov_vertical_deg": "",
      "fov_diagonal_deg": "Unklar",
      "resolution_per_eye": "Unklar",
      "refresh_hz": "Unklar",
      "weight_g": "38",
      "tracking": "None",
      "eye_tracking": "Nein",
      "hand_tracking": "Nein",
      "passthrough": "Nein (optische Durchsicht)",
      "chipset": "Unklar",
      "brightness_nits": "1000",
      "connectivity": "Bluetooth",
      "audio": "Open-ear",
      "battery": "Integriert",
      "ipd_mm": "Unklar",
      "prescription_support": "Unklar",
      "camera": "Nein",
      "sources": ["https://www.notebookcheck.net/OPPO-Air-Glass-2-debuts-as-a-new-light-and-accessibility-friendly-augmented-reality-product.674872.0.html", "https://www.gsmarena.com/hands_on_oppo_air_glass_2_zeropower_tag_and_wifi_6_router_at_mwc_2023-news-57744.php"],
      "confidence": "medium"
    },
    {
      "name": "Oppo Air Glass 3",
      "manufacturer": "Oppo",
      "official_url": "https://www.oppo.com/en/newsroom/press/oppo-unveils-new-oppo-air-glass-3/",
      "announced_date": "2024-02-26",
      "release_date": "2024",
      "price_usd": "Unklar",
      "xr_category": "AR",
      "active_distribution": "Nein",
      "eol_status": "Aktiv oder ohne EOL-Angabe",
      "eol_date": "",
      "lifecycle_notes": "Auf MWC 2024 als Prototyp gezeigte Vollfarb-Wellenleiterbrille mit eigenem Resin-Waveguide und AndesGPT-Assistent; kein kommerzieller Verkaufspreis.",
      "lifecycle_source": "https://www.oppo.com/en/newsroom/press/oppo-unveils-new-oppo-air-glass-3/",
      "software": "AndesGPT / Air Glass",
      "compute_unit": "Smartphone",
      "display_type": "Micro LED",
      "optics": "Waveguide",
      "fov_horizontal_deg": "",
      "fov_vertical_deg": "",
      "fov_diagonal_deg": "Unklar",
      "resolution_per_eye": "Unklar",
      "refresh_hz": "Unklar",
      "weight_g": "50",
      "tracking": "None",
      "eye_tracking": "Nein",
      "hand_tracking": "Nein",
      "passthrough": "Nein (optische Durchsicht)",
      "chipset": "Unklar",
      "brightness_nits": "1000",
      "connectivity": "Bluetooth",
      "audio": "In-ear Stereo, Vier-Mikrofon",
      "battery": "Integriert",
      "ipd_mm": "Unklar",
      "prescription_support": "Unklar",
      "camera": "Nein",
      "sources": ["https://www.oppo.com/en/newsroom/press/oppo-unveils-new-oppo-air-glass-3/", "https://techfocusonline.com/oppo-air-glass-3-full-guide-price-features-specs-release-date/amp/"],
      "confidence": "medium"
    },
    {
      "name": "vivo Vision Explorer Edition",
      "manufacturer": "vivo",
      "official_url": "https://www.vivo.com/",
      "announced_date": "2025-08-21",
      "release_date": "2025",
      "price_usd": "Unklar",
      "xr_category": "XR",
      "active_distribution": "Nein",
      "eol_status": "Aktiv oder ohne EOL-Angabe",
      "eol_date": "",
      "lifecycle_notes": "MR-Headset mit dualen 8K-Micro-OLED-Panels und Snapdragon XR2+ Gen 2; ab 22.08.2025 nur in chinesischen vivo-Stores demonstriert, kein Preis genannt.",
      "lifecycle_source": "https://www.gizmochina.com/2025/08/21/vivo-vision-explorer-edition-mr-headset-launched-specs-price/",
      "software": "OriginOS Vision",
      "compute_unit": "Standalone",
      "display_type": "Micro-OLED",
      "optics": "Pancake",
      "fov_horizontal_deg": "",
      "fov_vertical_deg": "",
      "fov_diagonal_deg": "",
      "resolution_per_eye": "3840x3552",
      "refresh_hz": "Unklar",
      "weight_g": "398",
      "tracking": "6DoF",
      "eye_tracking": "Ja",
      "hand_tracking": "Ja",
      "passthrough": "Vollfarb-Passthrough, 13 ms Latenz",
      "chipset": "Snapdragon XR2+ Gen 2",
      "brightness_nits": "Unklar",
      "connectivity": "Wi-Fi, Bluetooth",
      "audio": "Integriert",
      "battery": "Integriert / extern",
      "ipd_mm": "Unklar",
      "prescription_support": "Unklar",
      "camera": "7 externe Kameras (Passthrough/Tracking)",
      "sources": ["https://www.gizmochina.com/2025/08/21/vivo-vision-explorer-edition-mr-headset-launched-specs-price/", "https://m.gsmarena.com/vivo_vision_explorer_edition_mixed_reality_headset_goes_official-news-69149.php"],
      "confidence": "high"
    },
    {
      "name": "RayNeo Air 3s Pro",
      "manufacturer": "TCL",
      "official_url": "https://www.rayneo.com/products/ar-glasses-rayneo-air-3s-pro-features",
      "announced_date": "2025-05-27",
      "release_date": "2025-05-27",
      "price_usd": "299",
      "xr_category": "AR",
      "active_distribution": "Ja",
      "eol_status": "Aktiv oder ohne EOL-Angabe",
      "eol_date": "",
      "lifecycle_notes": "Birdbath-Kinobrille mit 1.200 nits HueView-2.0-Tandem-Micro-OLED; China (als Thunderbird Air 3s Pro) 1.599 CNY, international 299 USD.",
      "lifecycle_source": "https://www.tomshardware.com/peripherals/wearable-tech/rayneo-air-3s-pro-ar-glasses-review",
      "software": "Kein eigenes OS (DisplayPort)",
      "compute_unit": "Tethered",
      "display_type": "Micro-OLED",
      "optics": "Birdbath",
      "fov_horizontal_deg": "",
      "fov_vertical_deg": "",
      "fov_diagonal_deg": "46",
      "resolution_per_eye": "1920x1080",
      "refresh_hz": "120",
      "weight_g": "76",
      "tracking": "None",
      "eye_tracking": "Nein",
      "hand_tracking": "Nein",
      "passthrough": "Nein (optische Durchsicht)",
      "chipset": "Unklar",
      "brightness_nits": "1200",
      "connectivity": "USB-C DisplayPort",
      "audio": "Open-ear Stereo (3D Surround)",
      "battery": "Via Host-Geraet",
      "ipd_mm": "Unklar",
      "prescription_support": "Ja (Einsaetze)",
      "camera": "Nein",
      "sources": ["https://www.tomshardware.com/peripherals/wearable-tech/rayneo-air-3s-pro-ar-glasses-review", "https://www.ithome.com/0/856/405.htm"],
      "confidence": "high"
    },
    {
      "name": "RayNeo Air 1S",
      "manufacturer": "TCL",
      "official_url": "https://www.rayneo.com/",
      "announced_date": "2023-10",
      "release_date": "2023-10-20",
      "price_usd": "344",
      "xr_category": "AR",
      "active_distribution": "Nein",
      "eol_status": "EOL / Discontinued",
      "eol_date": "",
      "lifecycle_notes": "Erste Generation der Birdbath-Kinobrille (in China als Thunderbird Air 1S), Start zu 2.499 CNY (ca. 344 USD); inzwischen von Air 2/3-Serie abgeloest.",
      "lifecycle_source": "https://pandaily.com/thunderbird-innovation-releases-new-xr-glasses-for-2499-yuan/",
      "software": "Kein eigenes OS (DisplayPort)",
      "compute_unit": "Tethered",
      "display_type": "Micro-OLED",
      "optics": "Birdbath",
      "fov_horizontal_deg": "",
      "fov_vertical_deg": "",
      "fov_diagonal_deg": "Unklar",
      "resolution_per_eye": "1920x1080",
      "refresh_hz": "Unklar",
      "weight_g": "Unklar",
      "tracking": "None",
      "eye_tracking": "Nein",
      "hand_tracking": "Nein",
      "passthrough": "Nein (optische Durchsicht)",
      "chipset": "Unklar",
      "brightness_nits": "Unklar",
      "connectivity": "USB-C DisplayPort",
      "audio": "Open-ear Stereo",
      "battery": "Via Host-Geraet",
      "ipd_mm": "Unklar",
      "prescription_support": "Ja (Einsaetze)",
      "camera": "Nein",
      "sources": ["https://pandaily.com/thunderbird-innovation-releases-new-xr-glasses-for-2499-yuan/", "https://www.gizmochina.com/2023/10/13/thunderbird-air-2-smart-glasses/"],
      "confidence": "medium"
    },
    {
      "name": "Goolton Star1S",
      "manufacturer": "Goolton",
      "official_url": "https://goolton.com/ar-glasses/",
      "announced_date": "2024",
      "release_date": "2024-12",
      "price_usd": "Unklar",
      "xr_category": "AR",
      "active_distribution": "Unklar",
      "eol_status": "Aktiv oder ohne EOL-Angabe",
      "eol_date": "",
      "lifecycle_notes": "All-in-One-AR-Brille mit nach eigenen Angaben branchenweit erstem binokularen Vollfarb-Array-Wellenleiter und multimodalem KI-System; China-Verkauf ab Dezember 2024.",
      "lifecycle_source": "https://www.xrom.in/post/goolton-unveils-star1-and-star1s-ai-ar-glasses",
      "software": "Eigenes multimodales KI-System",
      "compute_unit": "Standalone",
      "display_type": "Micro-LED",
      "optics": "Waveguide",
      "fov_horizontal_deg": "",
      "fov_vertical_deg": "",
      "fov_diagonal_deg": "Unklar",
      "resolution_per_eye": "Unklar",
      "refresh_hz": "Unklar",
      "weight_g": "Unklar",
      "tracking": "None",
      "eye_tracking": "Nein",
      "hand_tracking": "Nein",
      "passthrough": "Nein (optische Durchsicht)",
      "chipset": "Unklar",
      "brightness_nits": "Unklar",
      "connectivity": "Wi-Fi, Bluetooth",
      "audio": "Open-ear",
      "battery": "Integriert",
      "ipd_mm": "Unklar",
      "prescription_support": "Unklar",
      "camera": "16 MP",
      "sources": ["https://www.xrom.in/post/goolton-unveils-star1-and-star1s-ai-ar-glasses", "https://www.aibase.com/news/13585"],
      "confidence": "medium"
    },
    {
      "name": "Goolton Star1",
      "manufacturer": "Goolton",
      "official_url": "https://goolton.com/ar-glasses/",
      "announced_date": "2024",
      "release_date": "2024-12",
      "price_usd": "Unklar",
      "xr_category": "AR",
      "active_distribution": "Unklar",
      "eol_status": "Aktiv oder ohne EOL-Angabe",
      "eol_date": "",
      "lifecycle_notes": "Getethertes (Split-Design) AR+AI-Brillenmodell mit binokularem Vollfarb-Wellenleiter, nur 80 g; China-Verkauf ab Dezember 2024, kein offizieller Preis genannt.",
      "lifecycle_source": "https://www.xrom.in/post/goolton-unveils-star1-and-star1s-ai-ar-glasses",
      "software": "Eigene AR/KI-Software",
      "compute_unit": "Tethered",
      "display_type": "Micro-LED",
      "optics": "Waveguide",
      "fov_horizontal_deg": "",
      "fov_vertical_deg": "",
      "fov_diagonal_deg": "Unklar",
      "resolution_per_eye": "Unklar",
      "refresh_hz": "Unklar",
      "weight_g": "80",
      "tracking": "None",
      "eye_tracking": "Nein",
      "hand_tracking": "Nein",
      "passthrough": "Nein (optische Durchsicht)",
      "chipset": "Unklar",
      "brightness_nits": "Unklar",
      "connectivity": "USB-C, Bluetooth",
      "audio": "Open-ear",
      "battery": "Via Host-Geraet",
      "ipd_mm": "Unklar",
      "prescription_support": "Unklar",
      "camera": "Unklar",
      "sources": ["https://www.xrom.in/post/goolton-unveils-star1-and-star1s-ai-ar-glasses", "https://www.webull.com/news/11866770770060288"],
      "confidence": "medium"
    },
    {
      "name": "INAIR Glasses",
      "manufacturer": "INAIR",
      "official_url": "https://inairspace.com/",
      "announced_date": "2024",
      "release_date": "2024",
      "price_usd": "650",
      "xr_category": "AR",
      "active_distribution": "Ja",
      "eol_status": "Aktiv oder ohne EOL-Angabe",
      "eol_date": "",
      "lifecycle_notes": "Birdbath-Display-Brille mit eigenem INAIR OS, 134-Zoll-Multifenster und Tastatur/Pod im Etui; in China fuer ca. 650 USD erhaeltlich.",
      "lifecycle_source": "https://inairspace.com/products/inair-glass",
      "software": "INAIR OS",
      "compute_unit": "Standalone",
      "display_type": "Micro-OLED",
      "optics": "Birdbath",
      "fov_horizontal_deg": "",
      "fov_vertical_deg": "",
      "fov_diagonal_deg": "Unklar",
      "resolution_per_eye": "1920x1080",
      "refresh_hz": "Unklar",
      "weight_g": "77",
      "tracking": "3DoF",
      "eye_tracking": "Nein",
      "hand_tracking": "Nein",
      "passthrough": "Nein (optische Durchsicht)",
      "chipset": "Qualcomm",
      "brightness_nits": "Unklar",
      "connectivity": "USB-C, Wi-Fi, Bluetooth",
      "audio": "Open-ear Stereo",
      "battery": "Integriert, ca. 4h",
      "ipd_mm": "Unklar",
      "prescription_support": "Unklar",
      "camera": "Nein",
      "sources": ["https://inairspace.com/products/inair-glass", "https://www.notebookcheck.net/Sharge-loomos-Smart-glasses-rated-to-take-4K-photos-and-play-Hi-Fi-audio.933247.0.html"],
      "confidence": "medium"
    },
    {
      "name": "INAIR 2 Pro",
      "manufacturer": "INAIR",
      "official_url": "https://inairspace.com/products/inair-2-pro-ar-glass",
      "announced_date": "2025",
      "release_date": "2025",
      "price_usd": "Unklar",
      "xr_category": "AR",
      "active_distribution": "Ja",
      "eol_status": "Aktiv oder ohne EOL-Angabe",
      "eol_date": "",
      "lifecycle_notes": "Birdbath-Brille mit dualen Micro-OLED, Echtzeit-2D-zu-3D und 135-Zoll-Multifenster; chinesischer Hersteller INAIR, internationaler Einzelhandelspreis variiert.",
      "lifecycle_source": "https://inairspace.com/products/inair-2-pro-ar-glass",
      "software": "INAIR OS",
      "compute_unit": "Tethered",
      "display_type": "Micro-OLED",
      "optics": "Birdbath",
      "fov_horizontal_deg": "",
      "fov_vertical_deg": "",
      "fov_diagonal_deg": "46",
      "resolution_per_eye": "1920x1080",
      "refresh_hz": "120",
      "weight_g": "Unklar",
      "tracking": "3DoF",
      "eye_tracking": "Nein",
      "hand_tracking": "Nein",
      "passthrough": "Nein (optische Durchsicht, elektrochrome Abdunklung)",
      "chipset": "Unklar",
      "brightness_nits": "500",
      "connectivity": "USB-C DisplayPort",
      "audio": "Open-ear Stereo",
      "battery": "Via Host-Geraet",
      "ipd_mm": "Unklar",
      "prescription_support": "Unklar",
      "camera": "Nein",
      "sources": ["https://inairspace.com/products/inair-2-pro-ar-glass", "https://www.amazon.com/INAIR-Multi-Screen-Entertainment-Compatible-iPhone15/dp/B0F2438Y1F"],
      "confidence": "medium"
    },
    {
      "name": "Rokid Max 2",
      "manufacturer": "Rokid",
      "official_url": "https://global.rokid.com/pages/rokid-max-2",
      "announced_date": "2025",
      "release_date": "2025",
      "price_usd": "529",
      "xr_category": "AR",
      "active_distribution": "Ja",
      "eol_status": "Aktiv oder ohne EOL-Angabe",
      "eol_date": "",
      "lifecycle_notes": "Birdbath-Kinobrille mit 1080p-Micro-OLED je Auge und simulierter Kruemmung (215-Zoll-Bild); Q1 2025 gestartet, UVP 529 USD.",
      "lifecycle_source": "https://www.androidcentral.com/gaming/virtual-reality/rokid-max-2-review",
      "software": "Kein eigenes OS (DisplayPort)",
      "compute_unit": "Tethered",
      "display_type": "Micro-OLED",
      "optics": "Birdbath",
      "fov_horizontal_deg": "",
      "fov_vertical_deg": "",
      "fov_diagonal_deg": "50",
      "resolution_per_eye": "1920x1080",
      "refresh_hz": "120",
      "weight_g": "75",
      "tracking": "None",
      "eye_tracking": "Nein",
      "hand_tracking": "Nein",
      "passthrough": "Nein (optische Durchsicht)",
      "chipset": "Unklar",
      "brightness_nits": "600",
      "connectivity": "USB-C DisplayPort",
      "audio": "Open-ear Stereo",
      "battery": "Via Host-Geraet",
      "ipd_mm": "Unklar",
      "prescription_support": "Ja (Einsaetze)",
      "camera": "Nein",
      "sources": ["https://www.androidcentral.com/gaming/virtual-reality/rokid-max-2-review", "https://www.amazon.com/Rokid-Max-AR-Glasses-Entertainment/dp/B0DKX1WSQ3"],
      "confidence": "high"
    },
    {
      "name": "Lenovo Legion AR Smart Glasses",
      "manufacturer": "Lenovo",
      "official_url": "https://www.lenovo.com/",
      "announced_date": "2025-07-14",
      "release_date": "2025-07",
      "price_usd": "348",
      "xr_category": "AR",
      "active_distribution": "Ja",
      "eol_status": "Aktiv oder ohne EOL-Angabe",
      "eol_date": "",
      "lifecycle_notes": "China-exklusive Gaming-Display-Brille mit 6.000-nits-Panel, 120 Hz und 2D-zu-3D-Wandlung; Start zu 2.499 CNY (ca. 348 USD).",
      "lifecycle_source": "https://www.technetbooks.com/2025/07/lenovo-legion-ar-smart-glasses-launch.html",
      "software": "Kein eigenes OS (DisplayPort)",
      "compute_unit": "Tethered",
      "display_type": "Micro-OLED",
      "optics": "Birdbath",
      "fov_horizontal_deg": "",
      "fov_vertical_deg": "",
      "fov_diagonal_deg": "Unklar",
      "resolution_per_eye": "1920x1080",
      "refresh_hz": "120",
      "weight_g": "63",
      "tracking": "None",
      "eye_tracking": "Nein",
      "hand_tracking": "Nein",
      "passthrough": "Nein (optische Durchsicht)",
      "chipset": "Unklar",
      "brightness_nits": "6000",
      "connectivity": "USB-C DisplayPort",
      "audio": "Dual-Lautsprecher",
      "battery": "Via Host-Geraet",
      "ipd_mm": "Unklar",
      "prescription_support": "Ja (Clips)",
      "camera": "Nein",
      "sources": ["https://www.technetbooks.com/2025/07/lenovo-legion-ar-smart-glasses-launch.html", "https://phandroid.com/2025/07/14/lenovos-new-legion-glasses-are-designed-for-gaming/"],
      "confidence": "medium"
    },
    {
      "name": "Skyworth PANCAKE 2",
      "manufacturer": "Skyworth",
      "official_url": "https://www.skyworthxr.com/",
      "announced_date": "2024-01",
      "release_date": "2024",
      "price_usd": "Unklar",
      "xr_category": "XR",
      "active_distribution": "Unklar",
      "eol_status": "Aktiv oder ohne EOL-Angabe",
      "eol_date": "",
      "lifecycle_notes": "MR-All-in-One mit Pancake-Optik und Micro-OLED (4K je Auge / 8K binokular), gezeigt auf CES 2024; kein offizieller Preis verfuegbar.",
      "lifecycle_source": "https://www.gizmochina.com/2024/01/11/skyworth-xr-mr-pancake-2-headset/",
      "software": "Unklar",
      "compute_unit": "Standalone",
      "display_type": "Micro-OLED",
      "optics": "Pancake",
      "fov_horizontal_deg": "",
      "fov_vertical_deg": "",
      "fov_diagonal_deg": "",
      "resolution_per_eye": "3840x3552",
      "refresh_hz": "Unklar",
      "weight_g": "Unklar",
      "tracking": "6DoF",
      "eye_tracking": "Ja",
      "hand_tracking": "Ja",
      "passthrough": "Vollfarb-VST-Passthrough (zwei Frontkameras)",
      "chipset": "Unklar",
      "brightness_nits": "Unklar",
      "connectivity": "Wi-Fi, Bluetooth",
      "audio": "Integriert",
      "battery": "Integriert",
      "ipd_mm": "Unklar",
      "prescription_support": "Unklar",
      "camera": "Ja (Passthrough)",
      "sources": ["https://www.gizmochina.com/2024/01/11/skyworth-xr-mr-pancake-2-headset/", "https://www.xrom.in/post/skyworth-pancake-2-set-to-make-a-grand-debut-at-ces-2024"],
      "confidence": "medium"
    },
    {
      "name": "RayNeo X3",
      "manufacturer": "TCL",
      "official_url": "https://www.rayneo.com/",
      "announced_date": "2025-01-07",
      "release_date": "2025",
      "price_usd": "Unklar",
      "xr_category": "AR",
      "active_distribution": "Unklar",
      "eol_status": "Aktiv oder ohne EOL-Angabe",
      "eol_date": "",
      "lifecycle_notes": "Auf CES 2025 vorgestellte Vollfarb-Wellenleiter-AI-AR-Brille mit Micro-LED; Standardvariante zur X3-Pro-Serie, ohne separat bestaetigten Verkaufspreis.",
      "lifecycle_source": "https://www.prnewswire.com/news-releases/rayneo-showcases-new-ar-lineup-at-ces-2025-302343690.html",
      "software": "RayNeo AR",
      "compute_unit": "Standalone",
      "display_type": "Micro-LED",
      "optics": "Waveguide",
      "fov_horizontal_deg": "",
      "fov_vertical_deg": "",
      "fov_diagonal_deg": "Unklar",
      "resolution_per_eye": "640x480",
      "refresh_hz": "60",
      "weight_g": "Unklar",
      "tracking": "None",
      "eye_tracking": "Nein",
      "hand_tracking": "Nein",
      "passthrough": "Nein (optische Durchsicht)",
      "chipset": "Snapdragon AR1",
      "brightness_nits": "Unklar",
      "connectivity": "Wi-Fi, Bluetooth",
      "audio": "Open-ear Stereo",
      "battery": "Integriert",
      "ipd_mm": "Unklar",
      "prescription_support": "Unklar",
      "camera": "Ja",
      "sources": ["https://www.prnewswire.com/news-releases/rayneo-showcases-new-ar-lineup-at-ces-2025-302343690.html", "https://xyzlabs.substack.com/p/rayneo-unveils-next-gen-ar-glasses"],
      "confidence": "medium"
    }
  ]
}
